stealthium/__init__.py
stealthium/browser.py
stealthium/proxy.py
stealthium/session.py
stealthium-0.1.0.dist-info/licenses/LICENSE
stealthium-0.1.0.dist-info/METADATA
stealthium-0.1.0.dist-info/WHEEL
stealthium-0.1.0.dist-info/top_level.txt
stealthium-0.1.0.dist-info/RECORD
