Metadata-Version: 2.4
Name: stealthium
Version: 0.1.0
Summary: Create undetectable browser sessions for web scraping without automation flags
Home-page: https://github.com/mohammedbenserya/stealthium
Author: BENSERYA MOHAMED
Author-email: BENSERYA MOHAMED <benseryamohammed1@gmail.com>
License: MIT
Project-URL: Homepage, https://github.com/mohammedbenserya/stealthium
Project-URL: Repository, https://github.com/mohammedbenserya/stealthium
Project-URL: Issues, https://github.com/mohammedbenserya/stealthium/issues
Keywords: web-scraping,selenium,browser,automation,stealth,anti-detection
Classifier: Development Status :: 3 - Alpha
Classifier: Intended Audience :: Developers
Classifier: License :: OSI Approved :: MIT License
Classifier: Programming Language :: Python :: 3
Classifier: Programming Language :: Python :: 3.8
Classifier: Programming Language :: Python :: 3.9
Classifier: Programming Language :: Python :: 3.10
Classifier: Programming Language :: Python :: 3.11
Classifier: Topic :: Internet :: WWW/HTTP :: Browsers
Classifier: Topic :: Software Development :: Libraries :: Python Modules
Requires-Python: >=3.8
License-File: LICENSE
Requires-Dist: requests>=2.28.0
Requires-Dist: selenium>=4.0.0
Requires-Dist: webdriver-manager>=3.8.0
Requires-Dist: fake-useragent>=1.1.0
Provides-Extra: linux
Requires-Dist: pyvirtualdisplay>=3.0; extra == "linux"
Dynamic: author
Dynamic: home-page
Dynamic: license-file
Dynamic: requires-python
